moplots/__init__.py
moplots/cli.py
moplots-0.1.2.post0.dist-info/LICENSE
moplots-0.1.2.post0.dist-info/METADATA
moplots-0.1.2.post0.dist-info/WHEEL
moplots-0.1.2.post0.dist-info/entry_points.txt
moplots-0.1.2.post0.dist-info/RECORD
