Metadata-Version: 2.1
Name: moplots
Version: 0.1.2.post0
Summary: Molecular Orbital Plots as Batch Series for ORCA
Home-page: https://github.com/Anselmoo/moplots
License: MIT
Author: Anselm Hahn
Author-email: anselm.hahn@gmail.com
Maintainer: Anselm Hahn
Maintainer-email: anselm.hahn@gmail.com
Requires-Python: >=3.7,<4.0
Classifier: Development Status :: 3 - Alpha
Classifier: Environment :: Console
Classifier: Intended Audience :: Science/Research
Classifier: License :: OSI Approved :: MIT License
Classifier: Operating System :: OS Independent
Classifier: Programming Language :: Python :: 3
Classifier: Programming Language :: Python :: 3.7
Classifier: Programming Language :: Python :: 3.8
Classifier: Programming Language :: Python :: 3.9
Classifier: Programming Language :: Python :: 3.10
Classifier: Programming Language :: Python :: 3.11
Classifier: Programming Language :: Python :: 3.12
Classifier: Programming Language :: Python :: Implementation :: CPython
Classifier: Topic :: Scientific/Engineering :: Chemistry
Classifier: Topic :: Scientific/Engineering :: Physics
Classifier: Topic :: Software Development :: Code Generators
Requires-Dist: rich (>=13.5.3,<14.0.0)
Requires-Dist: rich-argparse (>=1.3.0,<2.0.0)
Project-URL: Repository, https://github.com/Anselmoo/moplots
